jgs_container_image_utils/__init__.py
jgs_container_image_utils/_version.py
jgs_container_image_utils/load_image.py
jgs_container_image_utils-0.1.0.4884483917.dist-info/METADATA
jgs_container_image_utils-0.1.0.4884483917.dist-info/WHEEL
jgs_container_image_utils-0.1.0.4884483917.dist-info/entry_points.txt
jgs_container_image_utils-0.1.0.4884483917.dist-info/RECORD
