Metadata-Version: 2.1
Name: jgs-container-image-utils
Version: 0.1.0.4884483917
Summary: Helper programs for handling container images
Author-email: Jens Gwen Stein <jens.s.stein@gmail.com>
License: MIT
Requires-Python: >=3.10
